{
    "swagger": "2.0",
    "info": {
        "contact": {}
    },
    "paths": {
        "/auth/login": {
            "post": {
                "description": "login user, returns user and set session",
                "consumes": [
                    "application/json"
                ],
                "produces": [
                    "application/json"
                ],
                "tags": [
                    "Auth"
                ],
                "summary": "Login new user",
                "responses": {
                    "200": {
                        "description": "OK",
                        "schema": {
                            "$ref": "#/definitions/models.User"
                        }
                    }
                }
            }
        },
        "/auth/me": {
            "get": {
                "description": "Get current user by id",
                "consumes": [
                    "application/json"
                ],
                "produces": [
                    "application/json"
                ],
                "tags": [
                    "Auth"
                ],
                "summary": "Get user by id",
                "responses": {
                    "200": {
                        "description": "OK",
                        "schema": {
                            "$ref": "#/definitions/models.User"
                        }
                    },
                    "500": {
                        "description": "Internal Server Error",
                        "schema": {
                            "$ref": "#/definitions/httpErrors.RestError"
                        }
                    }
                }
            }
        },
        "/auth/register": {
            "post": {
                "description": "register new user, returns user and token",
                "consumes": [
                    "application/json"
                ],
                "produces": [
                    "application/json"
                ],
                "tags": [
                    "Auth"
                ],
                "summary": "Register new user",
                "responses": {
                    "201": {
                        "description": "Created",
                        "schema": {
                            "$ref": "#/definitions/models.User"
                        }
                    }
                }
            }
        },
        "/auth/{id}": {
            "get": {
                "description": "get string by ID",
                "consumes": [
                    "application/json"
                ],
                "produces": [
                    "application/json"
                ],
                "tags": [
                    "Auth"
                ],
                "summary": "get user by id",
                "parameters": [
                    {
                        "type": "integer",
                        "description": "user_id",
                        "name": "id",
                        "in": "path",
                        "required": true
                    }
                ],
                "responses": {
                    "200": {
                        "description": "OK",
                        "schema": {
                            "$ref": "#/definitions/models.User"
                        }
                    },
                    "500": {
                        "description": "Internal Server Error",
                        "schema": {
                            "$ref": "#/definitions/httpErrors.RestError"
                        }
                    }
                }
            },
            "put": {
                "description": "update existing user",
                "consumes": [
                    "application/json"
                ],
                "produces": [
                    "application/json"
                ],
                "tags": [
                    "Auth"
                ],
                "summary": "Update user",
                "parameters": [
                    {
                        "type": "integer",
                        "description": "user_id",
                        "name": "id",
                        "in": "path",
                        "required": true
                    }
                ],
                "responses": {
                    "200": {
                        "description": "OK",
                        "schema": {
                            "$ref": "#/definitions/models.User"
                        }
                    }
                }
            },
            "delete": {
                "description": "some description",
                "consumes": [
                    "application/json"
                ],
                "produces": [
                    "application/json"
                ],
                "tags": [
                    "Auth"
                ],
                "summary": "Delete user account",
                "parameters": [
                    {
                        "type": "integer",
                        "description": "user_id",
                        "name": "id",
                        "in": "path",
                        "required": true
                    }
                ],
                "responses": {
                    "200": {
                        "description": "ok",
                        "schema": {
                            "type": "string"
                        }
                    },
                    "500": {
                        "description": "Internal Server Error",
                        "schema": {
                            "$ref": "#/definitions/httpErrors.RestError"
                        }
                    }
                }
            }
        }
    },
    "definitions": {
        "httpErrors.RestError": {
            "type": "object",
            "properties": {
                "error": {
                    "type": "string"
                },
                "status": {
                    "type": "integer"
                }
            }
        },
        "models.User": {
            "type": "object",
            "required": [
                "first_name",
                "last_name",
                "password"
            ],
            "properties": {
                "avatar": {
                    "type": "array",
                    "items": {
                        "type": "integer"
                    }
                },
                "country": {
                    "type": "string",
                    "maxLength": 24
                },
                "created_at": {
                    "type": "string"
                },
                "email": {
                    "type": "string",
                    "maxLength": 60
                },
                "first_name": {
                    "type": "string",
                    "maxLength": 30
                },
                "last_name": {
                    "type": "string",
                    "maxLength": 30
                },
                "login_date": {
                    "type": "string"
                },
                "password": {
                    "type": "string",
                    "minLength": 6
                },
                "updated_at": {
                    "type": "string"
                },
                "user_id": {
                    "type": "string"
                }
            }
        }
    }
}